geist/__init__.py
geist/__main__.py
geist/api/connect.py
geist/api/create.py
geist/api/destroy.py
geist/api/export.py
geist/api/graph.py
geist/api/load.py
geist/api/query.py
geist/api/report.py
geist/commands/cli.py
geist/commands/create.py
geist/commands/destroy.py
geist/commands/export.py
geist/commands/graph.py
geist/commands/load.py
geist/commands/query.py
geist/commands/report.py
geist/datastore/duckdb.py
geist/datastore/rdflib.py
geist/tools/filters.py
geist/tools/globals.py
geist/tools/utils.py
geist_p-0.3.1.dist-info/LICENSE
geist_p-0.3.1.dist-info/METADATA
geist_p-0.3.1.dist-info/WHEEL
geist_p-0.3.1.dist-info/entry_points.txt
geist_p-0.3.1.dist-info/top_level.txt
geist_p-0.3.1.dist-info/RECORD
