Metadata-Version: 2.1
Name: geist-p
Version: 0.3.1
Summary: Geist: a multimodal data transformation, query, and reporting language
Home-page: https://cirss.github.io/geist-p/0.3/
Author: Meng Li, Timothy McPhillips, Bertram Ludäscher
Classifier: Programming Language :: Python :: 3.10
Classifier: Operating System :: OS Independent
Requires-Python: >=3.10
License-File: LICENSE
Requires-Dist: jinja2>=3.1.3
Requires-Dist: jinja2-simple-tags>=0.5.0
Requires-Dist: rdflib>=7.0.0
Requires-Dist: owlrl>=6.0.2
Requires-Dist: click>=8.1.7
Requires-Dist: pyarrow>=15.0.0
Requires-Dist: pandas>=2.2.0
Requires-Dist: tabulate>=0.9.0
Requires-Dist: pygraphviz>=1.12
Requires-Dist: duckdb>=0.10
Provides-Extra: dev
Requires-Dist: pytest>=7.0; extra == "dev"
Requires-Dist: twine>=4.0.2; extra == "dev"
